[
    {
        "pic" : "pictures/competences/html.png",
        "name" : "HTML",
        "desc" : "Langage de balisage WEB de base"
    },
    {
        "pic" : "pictures/competences/css.png",
        "name" : "CSS",
        "desc" : "Feuilles de style en cascade pour la mise en forme du HTML"
    },
    {
        "pic" : "pictures/competences/js.png",
        "name" : "JavaScript",
        "desc" : "Langage de programmation web"
    },
    {
        "pic" : "pictures/competences/php.png",
        "name" : "PHP",
        "desc" : "Langage de programmation WEB coté serveur"
    },
    {
        "pic" : "pictures/competences/sql.png",
        "name" : "SQL",
        "desc" : "Langage de requêtes structurées permettant de communiquer avec une base de données"
    },
    {
        "pic" : "pictures/competences/python.png",
        "name" : "Python",
        "desc" : "Langage de programmation interprété orienté objet"
    },
    {
        "pic" : "pictures/competences/java.png",
        "name" : "Java",
        "desc" : "Langage de programmation orienté objet"
    },
    {
        "pic" : "pictures/competences/bootstrap.png",
        "name" : "Bootstrap",
        "desc" : "Framework open-source orienté frontend et responsive"
    },
    {
        "pic" : "pictures/competences/symfony.jpg",
        "name" : "Symfony",
        "desc" : "Framework open-source pour PHP"
    },{
        "pic" : "pictures/competences/virtualbox.png",
        "name" : "Oracle VirtualBox",
        "desc" : "Logiciel libre de virtualisation"
    },
    {
        "pic" : "pictures/competences/git.png",
        "name" : "Git",
        "desc" : "Logiciel de gestion de versions open-source"
    }
]